{
  "node": [
    {
      "name": "eth-node0",
      "url": "$ETH_NODE_0_URL",
      "network": "ethereum",
      "env": "prod"
    },
    {
      "name": "llamanodes eth",
      "url": "$LLAMA_ETH_NODE_0_URL",
      "network": "ethereum",
      "env": "prod"
    },
    {
      "name": "cloudflare",
      "url": "https://cloudflare-eth.com/",
      "network": "ethereum",
      "env": "prod"
    },
    {
      "name": "ftm-node0",
      "url": "$FTM_NODE_0_URL",
      "network": "fantom",
      "env": "prod"
    },
    {
      "name": "ankr",
      "url": "https://rpc.ankr.com/fantom/",
      "network": "fantom",
      "env": "prod"
    },
    {
      "name": "arbi-node0",
      "url": "$ARBI_NODE_0_URL",
      "network": "arbitrum",
      "env": "prod"
    },
    {
      "name": "arbitrum public",
      "url": "https://arb1.arbitrum.io/rpc",
      "network": "arbitrum",
      "env": "prod"
    },
    {
      "name": "opti-node0",
      "url": "$OPTI_NODE_0_URL",
      "network": "optimism",
      "env": "prod"
    },
    {
      "name": "opti-node1",
      "url": "$OPTI_NODE_1_URL",
      "network": "optimism",
      "env": "prod"
    },
    {
      "name": "opti-node2",
      "url": "$OPTI_NODE_2_URL",
      "network": "optimism",
      "env": "prod"
    },
    {
      "name": "optimism public",
      "url": "https://mainnet.optimism.io",
      "network": "optimism",
      "env": "prod"
    },
    {
      "name": "avalanche public",
      "url": "https://rpc.ankr.com/avalanche",
      "network": "avalanche",
      "env": "prod"
    },
    {
      "name": "avax-node0",
      "url": "$AVAX_NODE_0_URL",
      "network": "avalanche",
      "env": "prod"
    },
    {
      "name": "polygon public",
      "url": "https://rpc.ankr.com/polygon",
      "network": "polygon",
      "env": "prod"
    },
    {
      "name": "poly-node0",
      "url": "$POLY_NODE_0_URL",
      "network": "polygon",
      "env": "prod"
    },
    {
      "name": "base public",
      "url": "https://rpc.ankr.com/base",
      "network": "base",
      "env": "prod"
    },
    {
      "name": "base-node0",
      "url": "$BASE_NODE_0_URL",
      "network": "base",
      "env": "prod"
    }
  ],
  "txPool": [
    {
      "name": "erigon txPool",
      "url": "$ETH_NODE_0_URL",
      "network": "ethereum",
      "env": "prod"
    }
  ],
  "website": [
    {
      "name": "yearn.vision",
      "url": "https://yearn.vision/?orgId=1&refresh=5m&viewPanel=17",
      "network": "ethereum",
      "env": "prod"
    },
    {
      "name": "yearn.finance",
      "url": "https://yearn.finance",
      "network": "ethereum",
      "env": "prod"
    }
  ],
  "apy": [
    {
      "name": "V1 API",
      "url": "https://api.yexporter.io/v1/chains/1/vaults/all",
      "network": "ethereum",
      "env": "prod"
    },
    {
      "name": "V1 API experimental",
      "url": "https://api.yexporter.io/v1/chains/1/vaults/experimental",
      "network": "ethereum",
      "env": "prod"
    },
    {
      "name": "V1 API",
      "url": "https://api.yexporter.io/v1/chains/250/vaults/all",
      "network": "fantom",
      "env": "prod"
    },
    {
      "name": "V1 API",
      "url": "https://api.yexporter.io/v1/chains/42161/vaults/all",
      "network": "arbitrum",
      "env": "prod"
    },
    {
      "name": "V1 API",
      "url": "https://api.yexporter.io/v1/chains/10/vaults/all",
      "network": "optimism",
      "env": "prod"
    },
    {
      "name": "Curve factory vaults APY previews",
      "url": "https://api.yexporter.io/v1/chains/1/apy-previews/curve-factory",
      "network": "ethereum",
      "env": "prod"
    }
  ],
  "api": [
    {
      "name": "yearn-exporter API",
      "url": "https://api.yearn.vision/tvl",
      "network": "ethereum",
      "env": "prod"
    },
    {
      "name": "yearn-exporter API arbitrum",
      "url": "https://api.yearn.vision/tvl/arb",
      "network": "arbitrum",
      "env": "prod"
    },
    {
      "name": "yearn-exporter API ethereum",
      "url": "https://api.yearn.vision/tvl/eth",
      "network": "ethereum",
      "env": "prod"
    },
    {
      "name": "yearn-exporter API fantom",
      "url": "https://api.yearn.vision/tvl/ftm",
      "network": "fantom",
      "env": "prod"
    },
    {
      "name": "yearn-exporter API optimism",
      "url": "https://api.yearn.vision/tvl/opt",
      "network": "optimism",
      "env": "prod"
    }
  ]
}
